MANIFEST.in
README.rst
setup.py
socketio_server/__init__.py
socketio_server/daemon.py
socketio_server/models.py
socketio_server/options.py
socketio_server/server.py
socketio_server/socketio_settings.sample.py
socketio_server/tests.py
socketio_server/utils.py
socketio_server.egg-info/PKG-INFO
socketio_server.egg-info/SOURCES.txt
socketio_server.egg-info/dependency_links.txt
socketio_server.egg-info/not-zip-safe
socketio_server.egg-info/requires.txt
socketio_server.egg-info/top_level.txt
socketio_server/management/__init__.py
socketio_server/management/commands/__init__.py
socketio_server/management/commands/socketio.py