Metadata-Version: 1.0
Name: socketio-server
Version: 0.0.9
Summary: Quick and dirty socketio server for django
Home-page: http://pypi.python.org/pypi/socketio-server/
Author: John Leith
Author-email: leith.john@gmail.com
License: UNKNOWN
Platform: UNKNOWN
